<annotation>
	<folder>JPEGImages</folder>
	<filename>jam3_0017.jpg</filename>
	<path>D:\资料\JPEGImages\jam3_0017.jpg</path>
	<source>
		<database>Unknown</database>
	</source>
	<size>
		<width>2592</width>
		<height>2048</height>
		<depth>3</depth>
	</size>
	<segmented>0</segmented>
	<object>
		<name>car</name>
		<pose>Unspecified</pose>
		<truncated>0</truncated>
		<difficult>0</difficult>
		<bndbox>
			<xmin>1243</xmin>
			<ymin>929</ymin>
			<xmax>1514</xmax>
			<ymax>1238</ymax>
		</bndbox>
	</object>
	<object>
		<name>car</name>
		<pose>Unspecified</pose>
		<truncated>0</truncated>
		<difficult>0</difficult>
		<bndbox>
			<xmin>959</xmin>
			<ymin>748</ymin>
			<xmax>1197</xmax>
			<ymax>964</ymax>
		</bndbox>
	</object>
	<object>
		<name>car</name>
		<pose>Unspecified</pose>
		<truncated>0</truncated>
		<difficult>0</difficult>
		<bndbox>
			<xmin>623</xmin>
			<ymin>1109</ymin>
			<xmax>1075</xmax>
			<ymax>1519</ymax>
		</bndbox>
	</object>
	<object>
		<name>car</name>
		<pose>Unspecified</pose>
		<truncated>0</truncated>
		<difficult>0</difficult>
		<bndbox>
			<xmin>117</xmin>
			<ymin>900</ymin>
			<xmax>359</xmax>
			<ymax>1016</ymax>
		</bndbox>
	</object>
</annotation>
