<annotation>
	<folder>JPEGImages</folder>
	<filename>jam4_0043.jpg</filename>
	<path>E:\JPEGImages\jam4_0043.jpg</path>
	<source>
		<database>Unknown</database>
	</source>
	<size>
		<width>2752</width>
		<height>2208</height>
		<depth>3</depth>
	</size>
	<segmented>0</segmented>
	<object>
		<name>car</name>
		<pose>Unspecified</pose>
		<truncated>0</truncated>
		<difficult>0</difficult>
		<bndbox>
			<xmin>919</xmin>
			<ymin>1303</ymin>
			<xmax>1357</xmax>
			<ymax>1810</ymax>
		</bndbox>
	</object>
	<object>
		<name>car</name>
		<pose>Unspecified</pose>
		<truncated>0</truncated>
		<difficult>0</difficult>
		<bndbox>
			<xmin>1732</xmin>
			<ymin>1441</ymin>
			<xmax>2264</xmax>
			<ymax>1924</ymax>
		</bndbox>
	</object>
	<object>
		<name>car</name>
		<pose>Unspecified</pose>
		<truncated>0</truncated>
		<difficult>0</difficult>
		<bndbox>
			<xmin>1536</xmin>
			<ymin>993</ymin>
			<xmax>1839</xmax>
			<ymax>1310</ymax>
		</bndbox>
	</object>
	<object>
		<name>car</name>
		<pose>Unspecified</pose>
		<truncated>0</truncated>
		<difficult>0</difficult>
		<bndbox>
			<xmin>1139</xmin>
			<ymin>976</ymin>
			<xmax>1446</xmax>
			<ymax>1238</ymax>
		</bndbox>
	</object>
	<object>
		<name>car</name>
		<pose>Unspecified</pose>
		<truncated>0</truncated>
		<difficult>0</difficult>
		<bndbox>
			<xmin>1350</xmin>
			<ymin>707</ymin>
			<xmax>1532</xmax>
			<ymax>855</ymax>
		</bndbox>
	</object>
</annotation>
